{"K8F":"IYM:1D:2CO:1IYM:2IYM:1wM:2IYM:11U:2FZ2:1FjG:2IYM:1Iyk:2IYM:1YIJ:2fPq:1FZ2:38:1D:2e:1M:20:1M:2H:1N:2Q:1N:2w:1a:2m:1Z:23:1W:2O:1P:2u:1x:2S:1n:21:1l:25:1Bh:2a:1Bg:2X:1Bi:2l:1Bi:2BA:1B8:2J:1Bb:2o:1Bb:2v:1Bl:22:1C=:2j:1Cf:2BD:1Cx:2c:1GR:27:1GR:2t:1GR:2-:1Td:2Y:1hv:2n:1C4l:2i:1FZ2:2FW7:1FZ2:2FjG:1FZ2:2Fjh:1FZ2:2IYM:1FZ2:2Nhv:1FZ2:2fPq:1FZ2:2iA8:1FZ2:2jLU:1JJg:26:1KbV:2x:1S=9:2LI1:1oKp:3:3","K8a":"E7x:1M:2tk:1HK:3C:1K:2K:1Bg:2N:1Hn:2D:1HK:2F:1HK:2M:1HK:2gJ:1HK:2I:1Sn:2H:1Cl4:2FAu:1mWf:3:3","K9Z":"G2c:1E:2E:1Vl2:2roP:1Ce:3B:1W:2Jh8:1CD:2MS4:1Bj:3:3","K8=":"EHm:1e:3Gwl:1C1:3:3","K9h":"cz:1HI:3Htg:1DI:3:3","K8w":"GX:1nJ:3SBh:1E-:3:3","K83":"WI:1Kf:2Chf:1Kf:2Kf:1nXX:3RaF:1Kf:2DhJ:1Uj:3:3","K81":"Kf:1Rb:2o3O:1Rb:3MJI:1Kf:2Kf:1d6P:3:3","K9S":"FZ:1cz:2cz:1TQ:2BRN:1cz:2BOc:1cz:3HZl:1NI:3:3","K9b":"FLy:1K:2FLy:1Ec:3B:1Je:2Ig:1V-:2ao:1tk:3:3","K9W":"MF:1VK:3MGb:1TZ:3:3","K8u":"GX:1mB:3Ns0:1mB:3:3","K8p":"Dt:1v4:2QE:1v4:2v4:1cz:2DaM:1v4:2FZ2:1v4:2Ib1:1l=:2IX3:1v4:2IX3:1Doe:2va:1ofB:3I9:1lx:2vz:1ZcJ:2Ga:1cRx:2P8:1fS1:2uE:1iCz:2Bjy:1jQi:2BMQ:1jQj:2Jys:1oGX:2fYx:1tA4:2mVK:1uZx:3:3","K8g":"E:1HbB:2C:1HbB:2Kq:1HbB:2NtW:1HbB:3J:1BNC:2E:1HbB:2B:1HbB:2WJ:1HbB:3:3","K8J":"GC:1lv:3BpG:1BPC:3:3","K9L":"mB:1GI:3Pi8:1BLK:3:3","K8f":"RA:1Lc:3OAj:1C-Z:3:3","K8n":"c8:1H9:2Bm0:1OB:3:3:3","K84":"D5:19W:2LG:1ST:3:3:3","K8i":"DH0:1-:2DH0:1Do:2X2:1BTs:2DH0:1OG:2DH0:1RN:2DH0:1Rk:2DH0:1VD:2DH0:1Xw:2DH0:1qU:2DH0:1bx:2DH0:1hJ:2DH0:1hb:2DH0:1xL:2DH0:1xK:2DH0:1vq:2DH0:1BSu:2DH0:1BTs:2DH0:1BSS:2DH0:1B7Q:2DH0:1CIr:2DH0:1DSy:2DH0:1DP6:2DH0:1DS2:2DH0:1DS4:2DH0:1DkR:2DH0:1EeR:2DH0:1D1Z:2Dwv:1DH0:2DH0:1HQc:2PYr:1EG8:3:3:3","K8S":"XU:1NR:2B7U:1Kk:2BRX:1hV:2azB:1GcC:3JHl:1nuB:3:3","K8E":"LG:1Vh:3M2s:1DnG:3:3","K8m":"2:1Cat:2I5o:1Dk:2I5o:1z3:2I5o:1zy:2I5o:1tG:2B7V:1R=h:3:3:3","K8M":"Kr:1S=:2Kr:1icI:3:3:3","K8y":"ig:1E5:2E5:1BZV:2BrL:1E5:2BDM:1ig:2BDF:1BrL:2Ib1:1E5:2BDF:1CYe:2NG:1QVw:3:3:3","K8A":"Qu:1MO:3:3:3","K8B":"MN:1VL:3:3:3","K8C":"Q0:1OB:2BEa:1OB:2Bkf:1OB:3:3:3","K8D":"Q0:1Ks:3:3:3","K8G":"a:1D5G:3:3:3","K8H":"a:1Dp4:3:3:3","K8I":"a:1Dyn:3:3:3","K8K":"lv:1FE:3FFE:1mWY:2MqY:1o4J:3:3","K8L":"3r:1CS:23r:13r:23r:1EVI:2laI:1Mn:2laI:1laI:3:3:3","K8N":"E2:1da:2BV5:1G1b:3:3:3","K8O":"E6:1g6:3:3:3","K8P":"d0:1FJ:3:3:3","K8Q":"XU:1NW:3:3:3","K8R":"XU:1Ma:3:3:3","K8T":"vQ:1DY:3:3:3","K8U":"Gw:1fI:3:3:3","K8V":"Q8:1I0:3:3:3","K8W":"BRJ:1Bs:3:3:3","K8X":"ig:1H9:2B9j:1ig:3:3:3","K8Y":"ig:1HI:2kR:1ig:2ig:1ki:2BUE:1ig:2BTN:1ig:3:3:3","K8Z":"ig:1GK:2ig:1B7z:3:3:3","K8b":"G6:1aT:2ig:1Q=:3:3:3","K8c":"os:1FO:3:3:3","K8d":"CG:1Byo:2CP:1Byo:3:3:3","K8e":"QQ:1MR:3:3:3","K8h":"CG:1B1B:3OSY:1pQY:3:3","K8j":"ll:1He:3:3:3","K8k":"kP:1HP:3M1f:1o5m:3:3","K8l":"kP:1HI:3:3:3","K8o":"RE:1OB:3:3:3","K8q":"GX:1eq:3:3:3","K8r":"kR:1GX:3:3:3","K8s":"GX:1qF:3:3:3","K8t":"GX:1e=:3:3:3","K8v":"GX:1bt:3:3:3","K8x":"E5:1a0:3:3:3","K8z":"E5:1bq:3:3:3","K80":"E5:1dE:2eX:1E5:3:3:3","K82":"XP:1Kf:2RBO:1Hfx:3:3:3","K85":"ST:1JD:3:3:3","K86":"ST:1JB:3:3:3","K87":"PI:1I6:3:3:3","K88":"RH:1N=:3:3:3","K89":"RH:1Nd:3:3:3","K8-":"S:1EHm:3:3:3","K9A":"EHm:1W:3:3:3","K9B":"EHm:1b:3:3:3","K9C":"v4:1Dr:2Bow:1Dr:3:3:3","K9D":"DmK:1e:3:3:3","K9E":"v4:1DF:3:3:3","K9F":"RJ:1Jt:3:3:3","K9G":"WJ:1L1:3:3:3","K9H":"RJ:1Ks:3:3:3","K9I":"L=:1Y9:2Fz:1CnH:2e0:1e0:2Lj:1CnH:20d:1CnH:3tf:1iHA:3:3","K9J":"XP:1Lz:3:3:3","K9K":"Lz:1V5:3:3:3","K9M":"RR:1LQ:2Jv:1Boj:3:3:3","K9N":"Hy:1e=:2Mk:1e=:3:3:3","K9O":"RL:1KW:3:3:3","K9P":"WI:1MT:3:3:3","K9Q":"MT:1S3:3IID:1nUu:3:3","K9R":"RL:1Ma:3:3:3","K9T":"XA:1LQ:3:3:3","K9U":"W5:1MF:2W5:1RF:3:3:3","K9V":"MF:1Sx:2MPz:1GCP:3M4U:1o33:3:3","K9X":"Hu:1mI:3:3:3","K9Y":"RO:1J-:3:3:3","K9a":"E-C:1G:3:3:3","K9c":"H5:1cz:2WI:1cz:3:3:3","K9d":"cz:1Hu:3:3:3","K9e":"cz:1FE:2cz:1JT:3LPs:1Ojf:3:3","K9f":"GS:1cz:3OJa:1pOs:3:3","K9g":"Gf:1cz:2BvO:1cz:3:3:3","K9i":"cz:1Gb:3:3:3","K9j":"ID:1cz:2cz:1dC:3:3:3"}