{"V-Q":"av:1xP:3:3:3","V-R":"av:19I:3:3:3","V-S":"Rr:1Bbd:2CjY:1Bbd:3:3:3","V-T":"XY:1B7X:2B7a:1W6d:3:3:3","V-U":"W=:1B7X:3:3:3","V-V":"Ri:1B7X:3:3:3","V-W":"O7:1B7X:3:3:3","V-X":"UU:1B7X:2UV:1B7X:2UV:1B7Q:3:3:3","V-Y":"Po:1B7X:3:3:3","V-Z":"zM:1qQ:2zM:1Bk7:2zM:1BPr:3:3:3","V-a":"zM:1nl:3:3:3","V-b":"c8:1zM:3:3:3","V-c":"XY:1BUk:3:3:3","V-d":"Zk:15k:3:3:3","V-e":"x=:1f3:2f3:1a0T:3:3:3","V-f":"dg:1BIi:3:3:3","V-g":"dg:15q:3:3:3","V-h":"CgI:1KO:3:3:3","V-i":"DG=:1K=:2DG=:1K9:3:3:3","V-j":"K=:1CgN:3:3:3","V-k":"SX:1BdQ:3:3:3","V-l":"BdO:1Yg:3:3:3","V-m":"cG:1yU:3:3:3","V-n":"yU:1aR:3:3:3","V-o":"yU:1di:3:3:3","V-p":"Q2:1B7U:2yU:1B7U:2BST:1B7U:2BST:1TR1:2nNM:1B7U:2nNM:1TR1:3:3:3","V-q":"yU:1de:2W-:1Xgb:2yU:1Xgb:2JEL:1Xgb:3:3:3","V-r":"yU:1Zk:3:3:3","V-s":"dg:1yU:3:3:3","V-t":"yU:1dH:3:3:3","V-u":"BJS:1jd:2BJS:1BZn:2BJS:1Cb9:3:3:3","V-v":"mf:1BJS:3:3:3","V-w":"gy:15B:3:3:3","V-x":"BBW:1nl:3:3:3","V-y":"1Z:1aA:2BBW:1aA:3:3:3","V-z":"1Z:1g8:2BBW:1g8:21Z:1ZoS:3:3:3","V-0":"BIw:1bz:3:3:3","V-1":"bz:19I:3:3:3","V-2":"B7U:1U4:2CTA:1azB:2Cfd:1azB:3:3:3","V-3":"Bk7:1U4:3:3:3","V-4":"BZn:1U4:2DF3:1U4:3:3:3","V-5":"BIw:1bA:2BIw:1BA1:2BIw:1Mbr:2BIw:1hc7:3:3:3","V-6":"bA:1xK:3:3:3","V-7":"zs:1bA:2zs:14e:3:3:3","V-8":"yU:1bA:3:3:3","V-9":"4y:1bA:3:3:3","V--":"14:1bA:3:3:3","V-=":"0q:1bA:3:3:3","V=A":"wH:1bA:3:3:3","V=B":"BJM:1bA:2BJM:1dn:2zx:1BJM:3:3:3","V=C":"wA:1bA:2ZXT:1hc7:3:3:3","V=D":"k6:15m:3:3:3","V=E":"f6:15m:2BmO:15m:2Cea:15m:3:3:3","V=F":"bn:15m:3:3:3","V=G":"hW:15m:3:3:3","V=H":"f3:15m:2CBE:15m:3:3:3","V=I":"mf:15m:3:3:3","V=J":"ct:15m:3:3:3","V=K":"hh:15m:3:3:3","V=L":"bz:10E:3:3:3","V=M":"0E:1hh:20E:1xX:3:3:3","V=N":"Zy:10E:3:3:3","V=O":"XY:1BPZ:3:3:3","V=P":"QZ:1B77:2QZ:1DBz:3:3:3","V=Q":"QZ:1B7b:3:3:3","V=R":"Km:1C3t:2GAb:1C3t:3:3:3","V=S":"DB1:1KT:3:3:3","V=T":"DB1:1KE:3:3:3","V=U":"L-:1DB1:3:3:3","V=V":"cG:104:3:3:3","V=W":"wA:1bl:2wA:104:3:3:3","V=X":"B77:1TG:3:3:3","V=Y":"Po:1B77:3:3:3","V=Z":"UO:1B7X:3:3:3","V=a":"B77:1Rr:3:3:3","V=b":"wW:1qV:3:3:3","V=c":"c8:1BIc:2c8:1BmO:3:3:3","V=d":"BIc:1cB:2BYK:1cB:3:3:3","V=e":"Zy:1BIc:3:3:3","V=f":"BIc:1hh:3:3:3","V=g":"JR:1Cea:3:3:3","V=h":"JR:1CgN:3:3:3","V=i":"yV:1cA:2BBW:1cA:2BQr:1cA:3:3:3","V=j":"yU:1cA:3:3:3","V=k":"cA:1-Q:3:3:3","V=l":"cA:1BIc:3:3:3","V=m":"Can:1JK:3:3:3","V=n":"Can:1No:2Can:1YS:2Can:1GFW:2Can:1ODE:2Can:1UO4:2Can:1XCS:2Can:1ds=:2Can:1dGm:2Can:1dWa:3:3:3","V=o":"BU6:1XY:3:3:3","V=p":"BU6:1Xu:3:3:3","V=q":"Wx:1BU6:3:3:3","V=r":"BU6:1W4:3:3:3","V=s":"3Q:1jo:3:3:3","V=t":"jo:147:3:3:3","V=u":"Bl-:1O7:3:3:3","V=v":"Bbd:1V=:3:3:3","V=w":"Wr:1B7X:3:3:3","V=x":"XD:1B7X:3:3:3","V=y":"XD:1BTs:2XD:1BSS:2XD:1CIg:2XD:1DS4:2XD:1YdS:2XD:1clP:3:3:3","V=z":"hv:1BIx:3:3:3"}