{"nTo":"e-:1a9c:3:3:3","nTp":"a5:1a9c:3:3:3","nTq":"a9c:1ae:2a9c:1Jre:3:3:3","nTr":"bh:1a9c:3:3:3","nTs":"a9c:1ej:2a9c:1NIJ:2a9c:1Yw=:2a9c:1dHY:2tLd:1BM:2tLd:1Or:2tLd:1ej:2tLd:1BC=:2tLd:1KbN:2tLd:1NGt:2tLd:1XAm:2tLd:1Yw=:2tLd:1deU:2tLd:1dHY:2tLd:1dSb:3:3:3","nTt":"a9c:1aU:2a9c:1XUL:3:3:3","nTu":"bR:1a9c:3:3:3","nTv":"eI:1a9c:3:3:3","nTw":"fu:1a9c:3:3:3","nTx":"a9c:1aC:3:3:3","nTy":"a9c:1bH:2a9c:1xp:2a9c:1rz:3:3:3","nTz":"aW:1a9c:3:3:3","nT0":"a9c:1l8:3:3:3","nT1":"a9c:1k=:3:3:3","nT2":"oV:1a9c:2OZp:1a9c:3:3:3","nT3":"ik:1a9c:3:3:3","nT4":"a9c:1cY:3:3:3","nT5":"a9c:1qa:3:3:3","nT6":"a9c:1me:3:3:3","nT7":"a9c:1p7:3:3:3","nT8":"pN:1a9c:3:3:3","nT9":"fT:1a9c:3:3:3","nT-":"a9c:1md:3:3:3","nT=":"bL:1a9c:3:3:3","nUA":"a9c:1oR:2a9c:1UJY:3:3:3","nUB":"a9c:1fX:3:3:3","nUC":"a9c:1ky:3:3:3","nUD":"h6:1a9c:3:3:3","nUE":"dO:1a9c:3:3:3","nUF":"a9c:1ov:3:3:3","nUG":"ou:1a9c:3:3:3","nUH":"f4:1a9c:2kWl:1a9c:3:3:3","nUI":"BEf:1ZCV:3:3:3","nUJ":"ZCV:1vP:3:3:3","nUK":"0F:1ZCV:3:3:3","nUL":"ZCV:1yO:3:3:3","nUM":"ZCV:1sP:2ZCV:1CDi:3:3:3","nUN":"ZCV:13R:3:3:3","nUO":"ZCV:1tW:3:3:3","nUP":"ZCV:10Y:3:3:3","nUQ":"ZCV:1th:3:3:3","nUR":"ZCV:13y:3:3:3","nUS":"ZCV:1tl:3:3:3","nUT":"BFW:1ZCV:3:3:3","nUU":"u8:1ZCV:3:3:3","nUV":"Edj:1Oxc:3:3:3","nUW":"Oxc:1EdJ:3:3:3","nUX":"Bzw:1WmI:3:3:3","nUY":"YN7:1xb:2YN7:1DOQ:3:3:3","nUZ":"YN7:1sY:3:3:3","nUa":"YN7:1BFY:3:3:3","nUb":"YN7:1tl:3:3:3","nUc":"BFW:1YN7:3:3:3","nUd":"YN7:1xC:3:3:3","nUe":"0Y:1YN7:3:3:3","nUf":"YN7:1BHA:3:3:3","nUg":"YN7:1tM:3:3:3","nUh":"YN7:1xi:2YN7:1J0t:3:3:3","nUi":"BHg:1YN7:3:3:3","nUj":"th:1YN7:3:3:3","nUk":"up:1YN7:3:3:3","nUl":"Ui1:1BzM:3:3:3","nUm":"B8h:1Ui1:3:3:3","nUn":"aSw:1e3:3:3:3","nUo":"aP:1aSw:3:3:3","nUp":"Fzu:1OfI:3:3:3","nUq":"F9S:1OfI:3:3:3","nUr":"GC8:1OfI:3:3:3","nUs":"F6S:1OfI:3:3:3","nUt":"X4:1bn7:2lfQ:1bn7:3:3:3","nUu":"YM:1bn7:3:3:3","nUv":"KuS:1HOq:3:3:3","nUw":"KuS:1HSs:3:3:3","nUx":"Ii-:1KuS:2UDV:1KuS:3:3:3","nUy":"JEo:1KuS:3:3:3","nUz":"P=:1cVZ:2hFI:1cVZ:3:3:3","nU0":"cVZ:1WE:3:3:3","nU1":"Pk:1cVZ:2Jak:1cVZ:3:3:3","nU2":"QB:1cVZ:3:3:3","nU3":"cVZ:1W5:3:3:3","nU4":"cVZ:1Wq:2qwY:1Wq:3:3:3","nU5":"cVZ:1Vx:2qwY:1OH:2qwY:1Vx:2qwY:1Vy:2qwY:1V0:3:3:3","nU6":"cVZ:1RH:3:3:3","nU7":"P0:1cVZ:3:3:3","nU8":"cVZ:1UZ:3:3:3","nU9":"cVZ:1Pi:3:3:3","nU-":"cVZ:1UT:3:3:3","nU=":"cVZ:1Pz:2cVZ:1VQ:2qwY:1VQ:3:3:3","nVA":"cVZ:1Tr:2Tr:1hCD:3:3:3","nVB":"S0:1cVZ:3:3:3","nVC":"Qq:1cVZ:2Tj:1cVZ:3:3:3","nVD":"cVZ:1WM:3:3:3","nVE":"cVZ:1Xt:3:3:3","nVF":"HM:1fdE:3:3:3","nVG":"fdE:1Ha:3:3:3","nVH":"gvi:1Cl:3:3:3","nVI":"gwI:1CV:2gvi:1Es:2gvi:1Gfz:3:3:3","nVJ":"gvi:1EC:3:3:3","nVK":"gvi:1DU:2gvi:1GE:2gvi:1BFO:3:3:3","nVL":"gvi:1Cs:3:3:3"}