{"lIk":"8r:1Rq3:3:3:3","lIl":"ye:1Rq3:3:3:3","lIm":"Rq3:15Z:3:3:3","lIn":"=Q:1Rq3:3:3:3","lIo":"vc:1Rq3:3:3:3","lIp":"Rq3:1zF:3:3:3","lIq":"1t:1Rq3:3:3:3","lIr":"Rq3:15m:3:3:3","lIs":"6S:1Rq3:3:3:3","lIt":"9k:1Rq3:3:3:3","lIu":"5F:1Rq3:3:3:3","lIv":"uR:1Rq3:3:3:3","lIw":"s5:1Rq3:3:3:3","lIx":"8v:1Rq3:3:3:3","lIy":"xw:1Rq3:3:3:3","lIz":"wA:1Rq3:3:3:3","lI0":"x5:1Rq3:3:3:3","lI1":"Rq3:1BHC:3:3:3","lI2":"vv:1Rq3:3:3:3","lI3":"Rq3:105:3:3:3","lI4":"vT:1Rq3:3:3:3","lI5":"xp:1Rq3:3:3:3","lI6":"vk:1Rq3:3:3:3","lI7":"BBW:1Rq3:3:3:3","lI8":"Rq3:14j:3:3:3","lI9":"=9:1Rq3:3:3:3","lI-":"uS:1Rq3:3:3:3","lI=":"0z:1Rq3:3:3:3","lJA":"zY:1Rq3:3:3:3","lJB":"ShB:10B:3:3:3","lJC":"ShB:10K:3:3:3","lJD":"ShB:1BBt:3:3:3","lJE":"ShB:18l:3:3:3","lJF":"=m:1ShB:3:3:3","lJG":"ShB:1xN:2ShB:1BZn:2ShB:1Cb9:2ShB:1UzW:2ShB:1ZKR:3:3:3","lJH":"ShB:1xM:3:3:3","lJI":"ShB:11M:3:3:3","lJJ":"9N:1ShB:3:3:3","lJK":"ShB:19W:3:3:3","lJL":"ShB:1BHC:3:3:3","lJM":"ShB:16E:3:3:3","lJN":"5Y:1ShB:3:3:3","lJO":"ShB:1yS:3:3:3","lJP":"yT:1R6J:3:3:3","lJQ":"R6J:1vv:3:3:3","lJR":"R6J:1xm:3:3:3","lJS":"R6J:18z:2R6J:1B7U:2azB:1mHt:3:3:3","lJT":"R6J:1wH:3:3:3","lJU":"R6J:1x5:2R6J:1ye:2R6J:1Bg-:2R6J:1CaS:2b2:1mHt:3:3:3","lJV":"R6J:1yR:3:3:3","lJW":"R6J:14m:2mHt:14m:3:3:3","lJX":"R6J:16b:2R6J:1BSS:3:3:3","lJY":"R6J:1uY:2Wru:1mHt:3:3:3","lJZ":"zh:1R6J:3:3:3","lJa":"R6J:1xw:2xw:1mHt:3:3:3","lJb":"R6J:1xG:3:3:3","lJc":"R6J:1zH:2R6J:1DmS:3:3:3","lJd":"R6J:1-Q:2R6J:1BQa:2mHt:1a8:3:3:3","lJe":"R6J:19v:2R6J:1CIg:3:3:3","lJf":"R6J:18r:3:3:3","lJg":"R6J:1vc:3:3:3","lJh":"3Q:1R6J:3:3:3","lJi":"R6J:16K:2R6J:19g:2mHt:16K:2mHt:19g:3:3:3","lJj":"R6J:1s=:3:3:3","lJk":"R6J:15m:2mHt:15m:3:3:3","lJl":"R6J:117:3:3:3","lJm":"R6J:1=Q:2=Q:1mHt:3:3:3","lJn":"1Z:1R6J:2yV:1R6J:2BQr:1R6J:3:3:3","lJo":"R6J:15S:3:3:3","lJp":"R6J:1wr:2R6J:1E=u:3:3:3","lJq":"R6J:1BEA:3:3:3","lJr":"R6J:1=j:3:3:3","lJs":"R6J:1zu:3:3:3","lJt":"R6J:1BHC:3:3:3","lJu":"R6J:1BA6:2R6J:1BdQ:3:3:3","lJv":"R6J:1yU:2EM:1mHt:3:3:3","lJw":"R6J:1z8:3:3:3","lJx":"R6J:14z:3:3:3","lJy":"R6J:10K:3:3:3","lJz":"5Y:1R6J:3:3:3","lJ0":"R6J:1y4:3:3:3","lJ1":"R6J:15k:2R6J:1DJq:3:3:3","lJ2":"6S:1R6J:2B3:1mHt:3:3:3","lJ3":"6h:1R6J:2R6J:1Vn=:3:3:3","lJ4":"R6J:14Y:3:3:3","lJ5":"R6J:1ta:3:3:3","lJ6":"R6J:12Y:3:3:3","lJ7":"R6J:1x8:3:3:3","lJ8":"vw:1R6J:2LvX:1R6J:3:3:3","lJ9":"R6J:10w:3:3:3","lJ-":"R6J:10D:3:3:3","lJ=":"R6J:18f:3:3:3","lKA":"R6J:19I:3:3:3","lKB":"s5:1R6J:3:3:3","lKC":"R6J:18v:3:3:3","lKD":"R6J:1tG:3:3:3","lKE":"R6J:1=9:3:3:3","lKF":"R6J:14U:2mHt:14U:2B7S:1mHt:2ZpJ:1mHt:3:3:3","lKG":"R6J:1z3:3:3:3","lKH":"zs:1R6J:3:3:3"}