{"X0L":{"from":[["JS","B7"]],"to":[],"hiddenFrom":[],"hiddenTo":[]},"X0d":{"from":[["JS","kt"]],"to":[],"hiddenFrom":[],"hiddenTo":[]},"Xzy":{"from":[["b9","h"]],"to":[],"hiddenFrom":[],"hiddenTo":[]},"Xzz":{"from":[["b9","f"]],"to":[],"hiddenFrom":[],"hiddenTo":[]},"Xzm":{"from":[["Sd","Ke"]],"to":[],"hiddenFrom":[],"hiddenTo":[]},"Xz3":{"from":[["b9","FE"]],"to":[],"hiddenFrom":[],"hiddenTo":[]},"X0M":{"from":[["JS","Z6"]],"to":[],"hiddenFrom":[],"hiddenTo":[]},"X0R":{"from":[["JS","JI"]],"to":[],"hiddenFrom":[],"hiddenTo":[]},"Xzf":{"from":[["Sd","ND"]],"to":[],"hiddenFrom":[],"hiddenTo":[]},"Xzl":{"from":[["Sd","Y6"]],"to":[],"hiddenFrom":[],"hiddenTo":[]},"Xz0":{"from":[["b9","Cg"]],"to":[],"hiddenFrom":[],"hiddenTo":[]},"Xz7":{"from":[["b9","Qr"]],"to":[],"hiddenFrom":[],"hiddenTo":[]},"X0N":{"from":[["JS","CO"]],"to":[],"hiddenFrom":[],"hiddenTo":[]},"X0O":{"from":[["JS","Co"]],"to":[],"hiddenFrom":[],"hiddenTo":[]},"X0Q":{"from":[["JS","U0"]],"to":[],"hiddenFrom":[],"hiddenTo":[]},"X0S":{"from":[["JS","Oc"]],"to":[],"hiddenFrom":[],"hiddenTo":[]},"X0V":{"from":[["JS","fg"]],"to":[],"hiddenFrom":[],"hiddenTo":[]},"X0a":{"from":[["JS","kn"]],"to":[],"hiddenFrom":[],"hiddenTo":[]},"X0n":{"from":[["JS","BO"]],"to":[],"hiddenFrom":[],"hiddenTo":[]},"X0r":{"from":[["JS","av"]],"to":[],"hiddenFrom":[],"hiddenTo":[]},"Xzc":{"from":[["Sd","iu"]],"to":[],"hiddenFrom":[],"hiddenTo":[]},"Xzd":{"from":[["Sd","OY"]],"to":[],"hiddenFrom":[],"hiddenTo":[]},"Xze":{"from":[["Sd","Hg"]],"to":[],"hiddenFrom":[],"hiddenTo":[]},"Xzg":{"from":[["Sd","NR"]],"to":[],"hiddenFrom":[],"hiddenTo":[]},"Xzi":{"from":[["Sd","Bv"]],"to":[],"hiddenFrom":[],"hiddenTo":[]},"Xzo":{"from":[["Sd","Hu"]],"to":[],"hiddenFrom":[],"hiddenTo":[]},"Xzq":{"from":[["Sd","Ov"]],"to":[],"hiddenFrom":[],"hiddenTo":[]},"Xzt":{"from":[["Sd","Q1"]],"to":[],"hiddenFrom":[],"hiddenTo":[]},"Xzu":{"from":[["Sd","WG"]],"to":[],"hiddenFrom":[],"hiddenTo":[]},"Xz5":{"from":[["b9","LC"]],"to":[],"hiddenFrom":[],"hiddenTo":[]},"Xz6":{"from":[["b9","NW"]],"to":[],"hiddenFrom":[],"hiddenTo":[]},"X0P":{"from":[["JS","IU"]],"to":[],"hiddenFrom":[],"hiddenTo":[]},"X0i":{"from":[["JS","Q3"]],"to":[],"hiddenFrom":[],"hiddenTo":[]},"X0q":{"from":[["JS","E5"]],"to":[],"hiddenFrom":[],"hiddenTo":[]},"X0v":{"from":[["JS","Nr"]],"to":[],"hiddenFrom":[],"hiddenTo":[]},"X0z":{"from":[["JS","Do"]],"to":[],"hiddenFrom":[],"hiddenTo":[]},"X08":{"from":[["JS","WG"]],"to":[],"hiddenFrom":[],"hiddenTo":[]},"Xzh":{"from":[["Sd","jH"]],"to":[],"hiddenFrom":[],"hiddenTo":[]},"Xzj":{"from":[["Sd","WJ"]],"to":[],"hiddenFrom":[],"hiddenTo":[]},"Xzr":{"from":[["Sd","Ps"]],"to":[],"hiddenFrom":[],"hiddenTo":[]},"Xzs":{"from":[["Sd","Jv"]],"to":[],"hiddenFrom":[],"hiddenTo":[]},"Xz9":{"from":[["b9","aA"]],"to":[],"hiddenFrom":[],"hiddenTo":[]},"X0G":{"from":[["b9","Do"]],"to":[],"hiddenFrom":[],"hiddenTo":[]},"X0T":{"from":[["JS","UZ"]],"to":[],"hiddenFrom":[],"hiddenTo":[]},"X0U":{"from":[["JS","an"]],"to":[],"hiddenFrom":[],"hiddenTo":[]},"X0W":{"from":[["JS","PX"]],"to":[],"hiddenFrom":[],"hiddenTo":[]},"X0Y":{"from":[["JS","XB"]],"to":[],"hiddenFrom":[],"hiddenTo":[]},"X0Z":{"from":[["JS","G-"]],"to":[],"hiddenFrom":[],"hiddenTo":[]},"X0c":{"from":[["JS","g4"]],"to":[],"hiddenFrom":[],"hiddenTo":[]},"X0f":{"from":[["JS","h0"]],"to":[],"hiddenFrom":[],"hiddenTo":[]},"X0g":{"from":[["JS","N+"]],"to":[],"hiddenFrom":[],"hiddenTo":[]},"X0l":{"from":[["JS","G0"]],"to":[],"hiddenFrom":[],"hiddenTo":[]},"X0m":{"from":[["JS","Qx"]],"to":[],"hiddenFrom":[],"hiddenTo":[]},"X0x":{"from":[["JS","RJ"]],"to":[],"hiddenFrom":[],"hiddenTo":[]},"X00":{"from":[["JS","HD"]],"to":[],"hiddenFrom":[],"hiddenTo":[]},"X01":{"from":[["JS","SJ"]],"to":[],"hiddenFrom":[],"hiddenTo":[]},"X02":{"from":[["JS","jU"]],"to":[],"hiddenFrom":[],"hiddenTo":[]},"X05":{"from":[["JS","g2"]],"to":[],"hiddenFrom":[],"hiddenTo":[]},"Xzk":{"from":[["gD","Sd"]],"to":[],"hiddenFrom":[],"hiddenTo":[]},"Xzn":{"from":[["d8","Sd"]],"to":[],"hiddenFrom":[],"hiddenTo":[]},"Xzp":{"from":[["Sd","au"]],"to":[],"hiddenFrom":[],"hiddenTo":[]},"Xzw":{"from":[["Wu","Sd"]],"to":[],"hiddenFrom":[],"hiddenTo":[]},"Xz1":{"from":[["b9","Jp"]],"to":[],"hiddenFrom":[],"hiddenTo":[]},"Xz8":{"from":[["b9","di"]],"to":[],"hiddenFrom":[],"hiddenTo":[]},"Xz+":{"from":[["b9","ij"]],"to":[],"hiddenFrom":[],"hiddenTo":[]},"X0D":{"from":[["b9","cf"]],"to":[],"hiddenFrom":[],"hiddenTo":[]},"X0H":{"from":[["b9","Qi"]],"to":[],"hiddenFrom":[],"hiddenTo":[]},"X0I":{"from":[["b9","GI"]],"to":[],"hiddenFrom":[],"hiddenTo":[]},"X0K":{"from":[["b9","O0"]],"to":[],"hiddenFrom":[],"hiddenTo":[]},"X0X":{"from":[["JS","RA"]],"to":[],"hiddenFrom":[],"hiddenTo":[]},"X0e":{"from":[["JS","hz"]],"to":[],"hiddenFrom":[],"hiddenTo":[]},"X0h":{"from":[["kV","JS"]],"to":[],"hiddenFrom":[],"hiddenTo":[]},"X0k":{"from":[["JS","HV"]],"to":[],"hiddenFrom":[],"hiddenTo":[]},"X0o":{"from":[["JS","Qe"]],"to":[],"hiddenFrom":[],"hiddenTo":[]},"X0s":{"from":[["JS","IR"]],"to":[],"hiddenFrom":[],"hiddenTo":[]},"X0t":{"from":[["JS","NY"]],"to":[],"hiddenFrom":[],"hiddenTo":[]},"X0u":{"from":[["JS","Mc"]],"to":[],"hiddenFrom":[],"hiddenTo":[]},"X0y":{"from":[["JS","Sp"]],"to":[],"hiddenFrom":[],"hiddenTo":[]},"X06":{"from":[["G6","JS"]],"to":[],"hiddenFrom":[],"hiddenTo":[]},"X07":{"from":[["e5","JS"]],"to":[],"hiddenFrom":[],"hiddenTo":[]},"X0-":{"from":[["JS","Sd"]],"to":[],"hiddenFrom":[],"hiddenTo":[]},"Xzv":{"from":[["gO","Sd"]],"to":[],"hiddenFrom":[],"hiddenTo":[]},"Xzx":{"from":[["L8","Sd"]],"to":[],"hiddenFrom":[],"hiddenTo":[]},"Xz2":{"from":[["b9","X5"]],"to":[],"hiddenFrom":[],"hiddenTo":[]},"X0A":{"from":[["b9","HV"]],"to":[],"hiddenFrom":[],"hiddenTo":[]},"X0F":{"from":[["b9","Ip"]],"to":[],"hiddenFrom":[],"hiddenTo":[]},"X0b":{"from":[["Qg","JS"]],"to":[],"hiddenFrom":[],"hiddenTo":[]},"X0p":{"from":[["WO","JS"]],"to":[],"hiddenFrom":[],"hiddenTo":[]},"X03":{"from":[["jT","JS"]],"to":[],"hiddenFrom":[],"hiddenTo":[]},"X09":{"from":[["Kv","JS"]],"to":[],"hiddenFrom":[],"hiddenTo":[]},"Xz4":{"from":[["b9","Wt"]],"to":[],"hiddenFrom":[],"hiddenTo":[]},"Xz-":{"from":[["cX","b9"]],"to":[],"hiddenFrom":[],"hiddenTo":[]},"X0j":{"from":[["Qs","JS"]],"to":[],"hiddenFrom":[],"hiddenTo":[]},"X0w":{"from":[["aT","JS"]],"to":[],"hiddenFrom":[],"hiddenTo":[]},"X04":{"from":[["bd","JS"]],"to":[],"hiddenFrom":[],"hiddenTo":[]},"X0+":{"from":[["R8","JS"]],"to":[],"hiddenFrom":[],"hiddenTo":[]},"X0B":{"from":[["TJ","b9"]],"to":[],"hiddenFrom":[],"hiddenTo":[]},"X0C":{"from":[["R8","b9"]],"to":[],"hiddenFrom":[],"hiddenTo":[]},"X0E":{"from":[["gj","b9"]],"to":[],"hiddenFrom":[],"hiddenTo":[]},"X0J":{"from":[["OJ","b9"]],"to":[],"hiddenFrom":[],"hiddenTo":[]}}