{"meg":"Ds;kkK;;;;;;;;;","meh":"DP;kkK;;;;;;;;;","mei":"EM;kkK;;;;;;;;;","mej":"Du;kkK;;;;;;;;;","mek":"Cp;kkK;;;;;;;;;","mel":"Y49;Qfu;;;;;;;;;","mem":"cXY;IPs;;;;;;;;;","men":"qG;iDz;;;;;;;;;","meo":"3K;iDz;;;;;;;;;","mep":"oj;iDz;;;;;;;;;","meq":"iDz;lp;;;;;;;;;","mer":"kr;iDz;;;;;;;;;","mes":"lw;iDz;;;;;;;;;","met":"xO;iDz;;;;;;;;;","meu":"mR;iDz;;;;;;;;;","mev":"ms;iDz;;;;;;;;;","mew":"kt;iDz;;;;;;;;;","mex":"pO;iDz;;;;;;;;;","mey":"sY;iDz;;;;;;;;;","mez":"we;iDz;;;;;;;;;","me0":"Lx-;bbw;;;;;;;;;","me1":"LeJ;bbw;;;;;;;;;","me2":"Ls1;bbw;;;;;;;;;","me3":"MN3;bbw;;;;;;;;;","me4":"Lx7;bbw;;;;;;;;;","me5":"LME;bbw;;;;;;;;;","me6":"fea;EAW;;;;;;;;;","me7":"YzP;PbD;;;;;;;;;","me8":"YzP;QsD;;;;;;;;;","me9":"YzP;Pku;;;;;;;;;","me-":"YzP;QaS;;;;;;;;;","me+":"QiG;YzP;;;;;;;;;","mfA":"YzP;Qfu;;;;;;;;;","mfB":"YzP;Pn0;;;;;;;;;","mfC":"Ydg;Q5I;;;;;;;;;","mfD":"ijI;fw;;ijI;Df2;;;;;;;;;","mfE":"ijI;jp;;;;;;;;;","mfF":"aSV;Ogc;;;;;;;;;","mfG":"QKX;ZIJ;;QKX;aSV;;;;;;;;;","mfH":"Ngy;aSV;;;;;;;;;","mfI":"YzP;Rau;;;;;;;;;","mfJ":"QOC;YzP;;;;;;;;;","mfK":"CXh;gGh;;;;;;;;;","mfL":"CQT;gGh;;;;;;;;;","mfM":"CEZ;gGh;;;;;;;;;","mfN":"DAr;gGh;;;;;;;;;","mfO":"doP;HEo;;;;;;;;;","mfP":"doP;HR-;;;;;;;;;","mfQ":"eOF;FNo;;;;;;;;;","mfR":"eOF;F7Q;;;;;;;;;","mfS":"eOF;FJ8;;;;;;;;;","mfT":"hhV;9P;;;;;;;;;","mfU":"hhV;BQ3;;;;;;;;;","mfV":"6y;hhV;;;;;;;;;","mfW":"6V;hhV;;;;;;;;;","mfX":"hhV;BI9;;;;;;;;;","mfY":"5o;hhV;;;;;;;;;","mfZ":"BMq;hhV;;;;;;;;;","mfa":"hhV;5q;;hhV;EUi;;;;;;;;;","mfb":"hhV;86;;;;;;;;;","mfc":"6W;hhV;;;;;;;;;","mfd":"BVa;hhV;;;;;;;;;","mfe":"52;hhV;;;;;;;;;","mff":"hhV;9h;;;;;;;;;","mfg":"hhV;BCy;;;;;;;;;","mfh":"hhV;+w;;;;;;;;;","mfi":"++;hhV;;;;;;;;;","mfj":"BVf;hhV;;;;;;;;;","mfk":"BXc;hhV;;;;;;;;;","mfl":"5w;hhV;;;;;;;;;","mfm":"hhV;BFg;;;;;;;;;","mfn":"BLV;hhV;;;;;;;;;","mfo":"BRQ;hhV;;;;;;;;;","mfp":"6-;hhV;;;;;;;;;","mfq":"6C;hhV;;;;;;;;;","mfr":"6c;hhV;;;;;;;;;","mfs":"XD;ijm;;;;;;;;;","mft":"XP6;TA4;;;;;;;;;","mfu":"DLh;ffe;;;;;;;;;","mfv":"DYE;ffe;;DYE;lDP;;DYE;lYz;;;;;;;;;","mfw":"DWF;ffe;;DWF;lDP;;;;;;;;;","mfx":"Do-;ffe;;;;;;;;;","mfy":"ECp;ffe;;;;;;;;;","mfz":"DST;ffe;;;;;;;;;","mf0":"EEx;ffe;;EEx;lDP;;EEx;lYz;;;;;;;;;","mf1":"DRw;ffe;;;;;;;;;","mf2":"Df2;ffe;;;;;;;;;","mf3":"DsW;ffe;;DsW;lDP;;;;;;;;;","mf4":"Dc9;ffe;;Dc9;lYz;;;;;;;;;","mf5":"Hvb;dQE;;;;;;;;;","mf6":"imM;ZU;;;;;;;;;","mf7":"imM;jY;;;;;;;;;","mf8":"imM;Y5;;;;;;;;;","mf9":"imM;Y9;;;;;;;;;","mf-":"b+;imM;;;;;;;;;","mf+":"imM;fV;;;;;;;;;","mgA":"imM;ZJ;;;;;;;;;","mgB":"imM;Yn;;;;;;;;;","mgC":"imM;ZA;;;;;;;;;","mgD":"imM;Xp;;;;;;;;;"}