{"VC4":"h8::aBml::c::c::c","VC5":"Bml::ag2::bBml::aRKH::blp3::aBml::c::c::c","VC6":"BXc::aqd::bBXc::aGY9::c::c::c","VC7":"BMf::aqd::c::c::c","VC8":"BNC::aqd::c::c::c","VC9":"BOK::aqd::bBOK::ajkF::c::c::c","VC-":"BLj::aqd::bBLj::aGY9::c::c::c","VC+":"BJT::aqd::c::c::c","VDA":"BVf::aqd::c::c::c","VDB":"CcT::aWJ::bCcT::aVy::bCcT::aDCy::c::c::c","VDC":"Uu::aCcT::c::c::c","VDD":"CcT::aP4::c::c::c","VDE":"PR::aCcT::c::c::c","VDF":"Pv::aCcT::bDzw::aBJU::bDzw::aBrv::bDzw::aCcT::bcX5::aDzw::c::c::c","VDG":"CcT::aOg::c::c::c","VDH":"0s::a++::c::c::c","VDI":"++::a4Q::c::c::c","VDJ":"wa::a++::bBTh::a++::c::c::c","VDK":"++::ax6::c::c::c","VDL":"++::a39::c::c::c","VDM":"zb::a++::c::c::c","VDN":"30::a++::c::c::c","VDO":"4f::a++::c::c::c","VDP":"jp::aB7d::c::c::c","VDQ":"B7d::aXW::bB7d::aBC4::bVqi::aJG::bB7d::aVqi::bB7d::af9a::c::c::c","VDR":"gl::aB7d::bnD::aB7d::c::c::c","VDS":"B7d::aYO::bB7d::aT-I::c::c::c","VDT":"B7d::aff::c::c::c","VDU":"gT::aB7d::c::c::c","VDV":"B7d::adB::c::c::c","VDW":"B7d::ad0::c::c::c","VDX":"HqW::aC1::c::c::c","VDY":"HqW::aDO::c::c::c","VDZ":"HqW::aDW::c::c::c","VDa":"HqW::aDD::bOag::aDD::c::c::c","VDb":"HqW::aC-::bHqW::aQE::c::c::c","VDc":"KQ::aDyp::bHqW::aKQ::b+F::aEIl::c::c::c","VDd":"HqW::aDo::c::c::c","VDe":"HqW::aDj::c::c::c","VDf":"HqW::aC9::c::c::c","VDg":"J2J::aCB::bOag::aCB::bJ2J::acN::bJ2J::amQ::bJ2J::amS::bJ2J::a6T::c::c::c","VDh":"J2J::aCG::c::c::c","VDi":"J2J::aBu::bJ2J::aEY::bJ2J::aCr::c::c::c","VDj":"J2J::aCL::bJ2J::aF+::bJ2J::aKY::bJ2J::aPd::bJ2J::aRE::bJ2J::aY5::bOag::aKY::bJ2J::ak8::bJ2J::akS::bJ2J::alK::bOag::aZq::bJ2J::aEUi::bOag::aCQT::bJ2J::aGo-::bJ2J::aSlq::c::c::c","VDk":"J2J::aBd::c::c::c","VDl":"J3E::aBQ::c::c::c","VDm":"J3E::aBY::c::c::c","VDn":"J3E::aBM::c::c::c","VDo":"J3E::aCI::c::c::c","VDp":"J3E::aBa::c::c::c","VDq":"J3E::aB6::c::c::c","VDr":"J3E::aBd::bJ3E::aEV::bJ3E::aF6::bJ3E::aGJ::bJ3E::aHk::bJ3E::aLF::bJ3E::aML::bJ3E::aPR::bJ3E::akr::bJ3E::aBn-::bJ3E::aBm9::bJ3E::aBpS::c::c::c","VDs":"J3E::aCH::c::c::c","VDt":"J3E::aBo::bJ3E::aW8::c::c::c","VDu":"J3E::aBc::c::c::c","VDv":"J3E::aBg::c::c::c","VDw":"J3E::aCG::c::c::c","VDx":"J3E::aB2::bJ3E::aEI::bOVK::aD7::bBn-::aOVK::c::c::c","VDy":"J3E::aB3::bJ3E::aJyw::c::c::c","VDz":"J3E::aBf::c::c::c","VD0":"J3E::aBu::c::c::c","VD1":"J3E::aBe::c::c::c","VD2":"J3E::aCO::c::c::c","VD3":"J3E::aB9::c::c::c","VD4":"J3E::aCC::c::c::c","VD5":"JpU::aBi::bJpU::aMN::c::c::c","VD6":"Fc+::aEu::bSpZ::aEu::bSpQ::aEu::c::c::c","VD7":"H6O::aCk::bQiO::aCk::c::c::c","VD8":"Fc+::aFJ::bQiO::aFJ::c::c::c","VD9":"Fc+::aH8::bJcC::aH8::bFc+::aBqp::bSpU::aH8::bQiO::aBqp::bSpU::aIiO::c::c::c","VD-":"H6O::aC7::c::c::c","VD+":"H6O::aC4::c::c::c","VEA":"H6O::aC+::c::c::c","VEB":"H6O::aDo::c::c::c","VEC":"Fc+::aHR::c::c::c","VED":"Fc+::aFi::c::c::c","VEE":"IBe::aCB::c::c::c","VEF":"JcE::aBL::c::c::c","VEG":"D90::aL0::bJcE::aD2::bJcE::aL0::bOzo::aD2::c::c::c","VEH":"JcE::aBm::bJcK::aBm::bLx-::aBm::bOWx::aBm::bQiG::aBm::c::c::c","VEI":"JcE::aCM::bJcE::aIL::bJcE::aN5::bJcE::aWa::bJcE::aV1::bJcE::aix::bJcE::abQ::bJcE::aYs::bJcE::aoP::bJcE::a3L::c::c::c","VEJ":"C9X::aPg::bD90::aPg::bJcE::aPg::bQiG::aPg::bkHg::aPg::c::c::c","VEK":"D90::aIs::bJcE::aIs::bOOB::aIs::c::c::c","VEL":"D90::aJh::bJcE::aJh::bOzo::aJh::bkHg::aJh::c::c::c","VEM":"D90::aIU::bJcE::aIU::bQiG::aIU::baDJ::aIU::c::c::c","VEN":"C9X::aSZ::bD90::aSZ::bJcE::aSZ::bQiG::aSZ::bQiH::aSZ::bkHg::aSZ::c::c::c","VEO":"JcE::aBR::bQiG::aBR::c::c::c","VEP":"JcE::aBq::c::c::c","VEQ":"C9X::aUy::bJcE::aUy::baDJ::aUy::c::c::c","VER":"C9X::aRZ::bD90::aRZ::bJcE::aRZ::bQiG::aRZ::bJcE::aC9X::bOzo::aC9X::bC9X::aRNz::baDJ::aRZ::bC9X::aaDJ::bON+::aaDJ::c::c::c","VES":"D90::aIg::bJcE::aIg::baDJ::aIg::bkHg::aIg::c::c::c","VET":"D90::aJe::bJcE::aJe::c::c::c","VEU":"D90::aI2::bFdD::aI2::bJcE::aI2::bOzo::aI2::bQiG::aI2::bUtm::aI2::baDJ::aI2::bkHg::aI2::c::c::c","VEV":"C9X::aQ9::bD90::aQ9::bFdE::aQ9::bFdF::aQ9::bJcE::aQ9::bJcC::aQ9::bMBu::aQ9::bOzo::aQ9::bQiG::aQ9::baDJ::aQ9::bkHg::aQ9::c::c::c","VEW":"C9X::aTN::bD90::aTN::bJcE::aTN::bJcC::aTN::bWv::aINk::bOzo::aTN::bkHg::aTN::c::c::c","VEX":"JcE::aBP::bJcK::aBP::bkHg::aBP::c::c::c","VEY":"C9X::aS5::bD90::aS5::bJcE::aS5::bkHg::aS5::c::c::c","VEZ":"D90::aJc::bJcE::aJc::c::c::c","VEa":"C9X::aQQ::bJcE::aQQ::bQiG::aQQ::c::c::c","VEb":"C9X::aQd::bD90::aQd::bJcE::aQd::c::c::c"}