{"Rj9":"4y::ahY::bCgY::a4y::c::c::c","RkP":"WS::aBXR::bbQ::aBXR::bha::aBXR::bBSI::aBXR::bQ+P::aBXR::c::c::c","Rkh":"Dzw::aCX::bDzw::aI1::baRd::aY2::baRd::aDzw::c::c::c","Rjc":"BIs::aWS::c::c::c","Rjd":"TU::aBIs::bTU::aESO::c::c::c","Rje":"BIs::aRJ::bESO::aRJ::c::c::c","Rjf":"Rj::aBIs::c::c::c","Rjg":"BIs::aWN::c::c::c","Rjh":"BIs::aPU::c::c::c","Rji":"BIs::aQM::bESO::aQM::c::c::c","Rjj":"BIs::aQQ::c::c::c","Rjk":"BIs::aPz::c::c::c","Rjl":"Pj::aBIs::c::c::c","Rjm":"BIs::aQX::bBIs::abbw::c::c::c","Rjn":"BIs::aSa::c::c::c","Rjo":"WO::aBIs::c::c::c","Rjp":"SO::aBIs::c::c::c","Rjq":"BIs::aRS::c::c::c","Rjr":"BIs::aTk::c::c::c","Rjs":"BIs::aQE::c::c::c","Rjt":"VG::aBIs::c::c::c","Rju":"BIs::aPY::c::c::c","Rjv":"Pr::aBIs::bPr::aESO::c::c::c","Rjw":"CU::aESO::c::c::c","Rjx":"Cx::aESO::c::c::c","Rjy":"G6T::a9::biQ::aG6T::c::c::c","Rjz":"G6T::a1::bG6T::aC1::bG6T::aX7::bG6T::alC::bG6T::a5w::bG6T::a5g::bG6T::aJ7T::bjKv::aDH::bZd::ajKv::bjKv::aup::bjKv::a-r::bjKv::aLyc::c::c::c","Rj0":"G6T::aBA::c::c::c","Rj1":"G6T::ao::bG6T::aPWF::c::c::c","Rj2":"BYx::aNa::c::c::c","Rj3":"BYx::aNo::c::c::c","Rj4":"CgY::aH9::bLK::aCgY::bJE::aCgY::bPG::aCgY::bCgY::azF::bBNC::aCgY::c::c::c","Rj5":"FJ::aCgY::c::c::c","Rj6":"CgY::aEw::bCgY::aEt::c::c::c","Rj7":"CgY::aEs::c::c::c","Rj8":"ID::aCgY::c::c::c","Rj-":"CgY::aFM::c::c::c","Rj+":"CgY::aGG::c::c::c","RkA":"CgY::aFS::bCgY::aBCX::c::c::c","RkB":"CgY::aHc::c::c::c","RkC":"CgY::aFT::c::c::c","RkD":"CgY::aE7::bCgY::adr1::c::c::c","RkE":"J::aMgc::bEz::aMgc::bMG::aMgc::bPG::aMgc::bOY::aMgc::bXU::aMgc::bX5::aMgc::bkx::aMgc::bpg::aMgc::blH::aMgc::bkn::aMgc::bBQS::aMgc::b55::aMgc::b99::aMgc::b5z::aMgc::b-O::aMgc::b6T::aMgc::bBX-::aMgc::bBX9::aMgc::bBYB::aMgc::bBkM::aMgc::bBYA::aMgc::bBYP::aMgc::bCEU::aMgc::bCLo::aMgc::bCEW::aMgc::bDDo::aMgc::bEau::aMgc::blRg::aMgc::c::c::c","RkF":"O::aMgc::bEb::aMgc::bO+B::aMgc::c::c::c","RkG":"Mgc::aG::c::c::c","RkH":"c::aIie::c::c::c","RkI":"Iie::aT::c::c::c","RkJ":"CB7::aKh::c::c::c","RkK":"Dzj::aDs::c::c::c","RkL":"HtZ::am::bHtZ::aFq::bN+::aHtZ::c::c::c","RkM":"h::aHtZ::c::c::c","RkN":"HtZ::a1::bHtZ::aBh::bHtZ::aC1::bHtZ::amg::bHtZ::a34::bHtZ::amU::bHtZ::aEGP::bHtZ::abZn::c::c::c","RkO":"HtZ::aBH::c::c::c","RkQ":"if::anJ::c::c::c","RkR":"Wv::anJ::bC9X::anJ::bD90::anJ::bFdD::anJ::bFdE::anJ::bJcK::anJ::bJcH::anJ::bMBu::anJ::bOzo::anJ::bQiG::anJ::baDJ::anJ::bkHg::anJ::c::c::c","RkU":"f4::anJ::bHve::anJ::baG0::anJ::c::c::c","RkS":"fc::anJ::c::c::c","RkT":"iI::anJ::bbZe::anJ::c::c::c","RkV":"ib::anJ::c::c::c","RkW":"f3::anJ::c::c::c","RkX":"fl::anJ::c::c::c","RkY":"iY::anJ::c::c::c","RkZ":"Dzw::aC+::c::c::c","Rka":"Dzw::aCu::bDzw::aKn::bDzw::aIs::c::c::c","Rkb":"Dzw::aDu::c::c::c","Rkc":"Dzw::aEP::bDzw::akL::bDzw::aox::c::c::c","Rkd":"Dzw::aDi::c::c::c","Rke":"Dzw::aC9::c::c::c","Rkf":"Dzw::aCt::bDzw::aO9::bDzw::aBXc::bDzw::aCB7::bDzw::aE+b::bDzw::aLEU::bS3p::aDzw::c::c::c","Rkg":"Dzw::aDd::bDzw::amp::bDzw::amM::bDzw::a5s::bDzw::aBCy::bDzw::aBxl::bDzw::aCFW::bDzw::aShy::c::c::c","Rki":"Dzw::aEk::c::c::c","Rkj":"Dzw::aDN::c::c::c","Rkk":"Dzw::aC5::bDzw::aGx::bDzw::aRLT::bDzw::ahfY::c::c::c","Rkl":"Dzw::aCa::bDzw::amD::bDzw::amw::bDzw::aBYA::c::c::c","Rkm":"Dzw::aDb::bDzw::aDo::bDzw::aFNP::c::c::c","Rkn":"Dzw::aEB::c::c::c","Rko":"Dzw::aCx::bDzw::aJC::bDzw::aBXN::bDzw::aEau::c::c::c","Rkp":"Dzw::aCb::c::c::c","Rkq":"Dzw::aDz::c::c::c","Rkr":"Dzw::aD3::c::c::c","Rks":"Dzw::aDC::bDzw::aC2::bDzw::a31::c::c::c","Rkt":"Dzw::aEN::bDzw::aBWa::c::c::c","Rku":"Dzw::aCg::bDzw::auS::bDzw::aBUH::bDzw::aU3U::c::c::c","Rkv":"Dzw::aDv::bDzw::a5-::bDzw::aQfu::c::c::c","Rkw":"Dzw::aDB::bDzw::alW::c::c::c","Rkx":"Dt::aDzw::c::c::c","Rky":"Dg::aDzw::c::c::c","Rkz":"Dzw::aC6::bDzw::a3R::bCxl::aDzw::bIua::aDzw::c::c::c","Rk0":"Dzw::aEe::c::c::c","Rk1":"Dzw::aCv::c::c::c","Rk2":"Dzw::aCe::bDzw::aJu::c::c::c","Rk3":"EK::aDzw::c::c::c","Rk4":"Dzw::aEG::c::c::c","Rk5":"Dzw::aDR::c::c::c","Rk6":"Dzw::aDH::c::c::c","Rk7":"Dzw::aCV::c::c::c","Rk8":"Dzw::aCr::c::c::c","Rk9":"Dzw::aDO::bDzw::aBZg::c::c::c","Rk-":"Dzw::aDY::c::c::c","Rk+":"Dzw::aCm::c::c::c"}